Jetson-stubs/METADATA.toml
Jetson-stubs/__init__.pyi
Jetson-stubs/py.typed
Jetson-stubs/GPIO/__init__.pyi
Jetson-stubs/GPIO/gpio.pyi
Jetson-stubs/GPIO/gpio_cdev.pyi
Jetson-stubs/GPIO/gpio_event.pyi
Jetson-stubs/GPIO/gpio_pin_data.pyi
types_jetson_gpio-2.1.11.20251002.dist-info/licenses/LICENSE
types_jetson_gpio-2.1.11.20251002.dist-info/METADATA
types_jetson_gpio-2.1.11.20251002.dist-info/WHEEL
types_jetson_gpio-2.1.11.20251002.dist-info/top_level.txt
types_jetson_gpio-2.1.11.20251002.dist-info/RECORD
